{
  "subtitle": "Where to have my baby?", 
  "description": "Pinakamainam magsilang sa paanakan", 
  "language": "fil_PH", 
  "title": "Saan ako dapat manganak?", 
  "primary_category": "a42d368e8fec4f6ebd150161854771c3", 
  "created_at": "2015-03-03T10:47:54+00:00", 
  "featured_in_category": false, 
  "modified_at": "2015-03-17T12:09:44.284547+00:00", 
  "_version": {
    "package_version": "1.0.0", 
    "language_version": "2.7.6", 
    "language_version_string": "2.7.6 (default, Mar 22 2014, 23:03:41) \n[GCC 4.8.2]", 
    "language": "python", 
    "package": "elastic-git"
  }, 
  "linked_pages": [], 
  "id": null, 
  "content": "Nilikha ng BabyCenter\r\n\r\nHabang papalapit ang oras ng iyong pagsilang, nararapat na magplano kung saan ka manganganak.\r\n\r\nMasisiguro ang kaligtasan mo at ng iyong sanggol kung ikaw ay manganganak sa pagamutan o ospital. Mainam ito dahil agad na mareresolba kung magkaroon man ng problema. Ang pinakaligtas na lugar para sa iyong panganganak ay sa ospital o paanakan.\r\n\r\nNararapat na isipin mo kung gaano katagal ang byahe patungo sa ospital o paanakan mula sa inyong tahanan. Kausapin ang iyong mga kaanak at alamin kung sino ang maaaring sumama sa iyo at kung paano ka madadala rito. Siguruhing magpasama sa taong iyong mapagkakatiwalaan. \r\n", 
  "source": "21afd5d9e8d9433e876431e5fcb1cef0", 
  "featured": false, 
  "author_tags": [], 
  "image": null, 
  "published": null, 
  "position": 54, 
  "image_host": "http://thumbor.unicore.io", 
  "slug": "saan-ako-dapat-manganak", 
  "uuid": "a7a0db3a51424f209d391df45374707b"
}