{
  "subtitle": "Hindi ako dinatnan ng isang buwan.", 
  "description": "Hindi ako dinatnan ng isang buwan.", 
  "language": "fil_PH", 
  "title": "Buntis ba ako?", 
  "primary_category": "a42d368e8fec4f6ebd150161854771c3", 
  "created_at": "2015-03-03T09:24:18+00:00", 
  "featured_in_category": false, 
  "modified_at": "2015-03-03T09:32:39.593679+00:00", 
  "_version": {
    "package_version": "1.0.0", 
    "language_version": "2.7.6", 
    "language_version_string": "2.7.6 (default, Mar 22 2014, 23:03:41) \n[GCC 4.8.2]", 
    "language": "python", 
    "package": "elastic-git"
  }, 
  "linked_pages": [], 
  "id": null, 
  "content": "Nilikha ni BabyCenter\r\n\r\nBuntis ka ba? Paano mo malalaman kung ikaw nga ay nagdadalang-tao? Isa sa mga senyales ang hindi pagdating ng iyong mens ng isang buwan. Pero maaaring hindi mo na matandaan kung kalian ka huling dinatnan.\r\n\r\nNararanasan mo ba ang mga sumusunod ?\r\n\r\n - Iba ang pakiramdam at hitsura ng iyong mga suso\r\n - May mga bahid ng dugo sa iyong panty\r\n - Pagkahilo\r\n - Madalas na pag-ihi\r\n - Madaling mapagod\r\n - Hindi dumating ang mens ng isang buwan o higit pa\r\n\r\nKung sa tingin mo ikaw ay nagdadalang-tao, makabubuting kumonsulta ka sa isang komadrona, nurse, o doktor. Maiging makasiguro ka ng mas maaga dahil mas mapagpaplanuhan mo ang pagdating ng iyong sanggol. Makatutulong sa iyo ang komadrona, nurse, o doktor habang ikaw ay nagdadalang-tao.\r\n\r\nSa iyong pagbisita sa komadrona, nurse, o doktor, titimbangin ka nila, susukatin ang iyong blood pressure, at eeksaminin ang iyong panubigan.\r\n\r\nNag-aalala k aba o nag-aalinlangan sa pagpunta sa komadrona, nurse, o doktor? Pwede kang magpasama sa kamag-anak o kaibigan.", 
  "source": "fef097f5f22a4336b8577ff6f9e5427e", 
  "featured": false, 
  "author_tags": [], 
  "image": null, 
  "published": null, 
  "position": 3, 
  "image_host": "http://thumbor.unicore.io", 
  "slug": "buntis-ba-ako", 
  "uuid": "ceb2054ed5c8433581ee078ec984cd64"
}